pipeline_sdk_test71/__init__.py
pipeline_sdk_test71/auth_service.py
pipeline_sdk_test71/inference_pipeline.py
pipeline_sdk_test71/model_inference_dsl_component.py
pipeline_sdk_test71/model_train_dsl_component.py
pipeline_sdk_test71/model_validate_dsl_component.py
pipeline_sdk_test71/pipeline_util.py
pipeline_sdk_test71/run_inference_pipeline.py
pipeline_sdk_test71/run_training_pipeline.py
pipeline_sdk_test71/run_validate_pipeline.py
pipeline_sdk_test71/train_pipeline.py
pipeline_sdk_test71/validate_pipeline.py
pipeline_sdk_test71-1.0.0.dist-info/METADATA
pipeline_sdk_test71-1.0.0.dist-info/WHEEL
pipeline_sdk_test71-1.0.0.dist-info/top_level.txt
pipeline_sdk_test71-1.0.0.dist-info/RECORD
